mymask/__init__.py
mymask/__main__.py
mymask/app.py
mymask/icon.png
mymask-0.1.7.dist-info/LICENSE
mymask-0.1.7.dist-info/METADATA
mymask-0.1.7.dist-info/WHEEL
mymask-0.1.7.dist-info/entry_points.txt
mymask-0.1.7.dist-info/top_level.txt
mymask-0.1.7.dist-info/RECORD
