Metadata-Version: 2.1
Name: mymask
Version: 0.1.7
Summary: An interactive data masking tool for any x-y data
Home-page: https://github.com/lmytime/mymask
Author: Mingyu Li
Author-email: lmytime@hotmail.com
License: GPL3
Classifier: Programming Language :: Python :: 3
Classifier: License :: OSI Approved :: GNU General Public License v3 (GPLv3)
Classifier: Operating System :: OS Independent
Requires-Python: >=3.6
License-File: LICENSE
Requires-Dist: numpy
Requires-Dist: pandas
Requires-Dist: astropy
Requires-Dist: PyQt5
Requires-Dist: matplotlib
